{
  "dashboard": {
    "id": null,
    "title": "StopSign AI - Business Intelligence & Traffic Analysis",
    "tags": ["stopsign", "business", "traffic", "ai"],
    "timezone": "browser",
    "refresh": "30s",
    "time": {
      "from": "now-24h",
      "to": "now"
    },
    "panels": [
      {
        "id": 1,
        "title": "ðŸš— Vehicles Detected Today",
        "type": "stat",
        "targets": [
          {
            "rawSql": "SELECT sum(toFloat64OrNull(SpanAttributes['objects.detected_count'])) as vehicles_today FROM otel_traces WHERE SpanName = 'yolo_inference' AND SpanAttributes['objects.detected_count'] != '' AND Timestamp >= today()",
            "refId": "A"
          }
        ],
        "fieldConfig": {
          "defaults": {
            "unit": "short",
            "color": {
              "mode": "palette-classic"
            }
          }
        },
        "gridPos": { "h": 8, "w": 4, "x": 0, "y": 0 }
      },
      {
        "id": 2,
        "title": "ðŸ›‘ Stop Sign Compliance Rate",
        "type": "gauge",
        "targets": [
          {
            "rawSql": "SELECT (countIf(toFloat64OrNull(SpanAttributes['violations.detected_count']) = 0) * 100.0 / count()) as compliance_rate FROM otel_traces WHERE SpanName = 'stop_detection' AND SpanAttributes['violations.detected_count'] != '' AND Timestamp >= now() - INTERVAL 24 HOUR",
            "refId": "A"
          }
        ],
        "fieldConfig": {
          "defaults": {
            "unit": "percent",
            "min": 0,
            "max": 100,
            "color": {
              "mode": "thresholds"
            },
            "thresholds": {
              "values": [
                { "color": "red", "value": 0 },
                { "color": "yellow", "value": 60 },
                { "color": "green", "value": 80 }
              ]
            }
          }
        },
        "gridPos": { "h": 8, "w": 4, "x": 4, "y": 0 }
      },
      {
        "id": 3,
        "title": "âš ï¸ Violations This Hour",
        "type": "stat",
        "targets": [
          {
            "rawSql": "SELECT sum(toFloat64OrNull(SpanAttributes['violations.detected_count'])) as violations_hour FROM otel_traces WHERE SpanName = 'stop_detection' AND SpanAttributes['violations.detected_count'] != '' AND toFloat64OrNull(SpanAttributes['violations.detected_count']) > 0 AND Timestamp >= now() - INTERVAL 1 HOUR",
            "refId": "A"
          }
        ],
        "fieldConfig": {
          "defaults": {
            "unit": "short",
            "color": {
              "mode": "thresholds"
            },
            "thresholds": {
              "values": [
                { "color": "green", "value": 0 },
                { "color": "yellow", "value": 1 },
                { "color": "red", "value": 5 }
              ]
            }
          }
        },
        "gridPos": { "h": 8, "w": 4, "x": 8, "y": 0 }
      },
      {
        "id": 4,
        "title": "ðŸ‘¥ Active Vehicle Tracking",
        "type": "stat",
        "targets": [
          {
            "rawSql": "SELECT avg(toFloat64OrNull(SpanAttributes['cars.after_count'])) as avg_tracked FROM otel_traces WHERE SpanName = 'car_tracking' AND SpanAttributes['cars.after_count'] != '' AND Timestamp >= now() - INTERVAL 5 MINUTE",
            "refId": "A"
          }
        ],
        "fieldConfig": {
          "defaults": {
            "unit": "short",
            "color": {
              "mode": "palette-classic"
            }
          }
        },
        "gridPos": { "h": 8, "w": 4, "x": 12, "y": 0 }
      },
      {
        "id": 5,
        "title": "ðŸŽ¯ AI Detection Accuracy",
        "type": "stat",
        "targets": [
          {
            "rawSql": "SELECT avg(toFloat64OrNull(SpanAttributes['objects.detected_count']) / toFloat64OrNull(SpanAttributes['detections.input_count'])) * 100 as detection_rate FROM otel_traces WHERE SpanName = 'car_tracking' AND SpanAttributes['objects.detected_count'] != '' AND SpanAttributes['detections.input_count'] != '' AND Timestamp >= now() - INTERVAL 1 HOUR",
            "refId": "A"
          }
        ],
        "fieldConfig": {
          "defaults": {
            "unit": "percent",
            "color": {
              "mode": "thresholds"
            },
            "thresholds": {
              "values": [
                { "color": "red", "value": 0 },
                { "color": "yellow", "value": 70 },
                { "color": "green", "value": 85 }
              ]
            }
          }
        },
        "gridPos": { "h": 8, "w": 4, "x": 16, "y": 0 }
      },
      {
        "id": 6,
        "title": "â±ï¸ Average YOLO Inference Time",
        "type": "stat",
        "targets": [
          {
            "rawSql": "SELECT avg(toFloat64OrNull(SpanAttributes['inference.duration_seconds'])) * 1000 as avg_inference_ms FROM otel_traces WHERE SpanName = 'yolo_inference' AND SpanAttributes['inference.duration_seconds'] != '' AND Timestamp >= now() - INTERVAL 1 HOUR",
            "refId": "A"
          }
        ],
        "fieldConfig": {
          "defaults": {
            "unit": "ms",
            "color": {
              "mode": "palette-classic"
            }
          }
        },
        "gridPos": { "h": 8, "w": 4, "x": 20, "y": 0 }
      },
      {
        "id": 7,
        "title": "ðŸ“Š Traffic Patterns - Hourly Detection Volume",
        "type": "timeseries",
        "targets": [
          {
            "rawSql": "SELECT toStartOfHour(Timestamp) as time, sum(toFloat64OrNull(SpanAttributes['objects.detected_count'])) as vehicles_detected FROM otel_traces WHERE SpanName = 'yolo_inference' AND SpanAttributes['objects.detected_count'] != '' AND Timestamp >= now() - INTERVAL 24 HOUR GROUP BY time ORDER BY time",
            "refId": "A"
          }
        ],
        "fieldConfig": {
          "defaults": {
            "unit": "short",
            "color": {
              "mode": "palette-classic"
            }
          }
        },
        "gridPos": { "h": 8, "w": 12, "x": 0, "y": 8 }
      },
      {
        "id": 8,
        "title": "ðŸš¨ Violation Trend Analysis",
        "type": "timeseries",
        "targets": [
          {
            "rawSql": "SELECT toStartOfHour(Timestamp) as time, sum(toFloat64OrNull(SpanAttributes['violations.detected_count'])) as violations, count() as total_events FROM otel_traces WHERE SpanName = 'stop_detection' AND SpanAttributes['violations.detected_count'] != '' AND Timestamp >= now() - INTERVAL 24 HOUR GROUP BY time ORDER BY time",
            "refId": "A"
          }
        ],
        "fieldConfig": {
          "defaults": {
            "unit": "short",
            "color": {
              "mode": "palette-classic"
            }
          }
        },
        "gridPos": { "h": 8, "w": 12, "x": 12, "y": 8 }
      },
      {
        "id": 9,
        "title": "ðŸ§  AI Model Performance Trends",
        "type": "timeseries",
        "targets": [
          {
            "rawSql": "SELECT toStartOfHour(Timestamp) as time, avg(toFloat64OrNull(SpanAttributes['inference.duration_seconds'])) * 1000 as avg_inference_ms, quantile(0.95)(toFloat64OrNull(SpanAttributes['inference.duration_seconds'])) * 1000 as p95_inference_ms FROM otel_traces WHERE SpanName = 'yolo_inference' AND SpanAttributes['inference.duration_seconds'] != '' AND Timestamp >= now() - INTERVAL 24 HOUR GROUP BY time ORDER BY time",
            "refId": "A"
          }
        ],
        "fieldConfig": {
          "defaults": {
            "unit": "ms",
            "color": {
              "mode": "palette-classic"
            }
          }
        },
        "gridPos": { "h": 8, "w": 8, "x": 0, "y": 16 }
      },
      {
        "id": 10,
        "title": "ðŸŽ¯ Detection vs Tracking Efficiency",
        "type": "timeseries",
        "targets": [
          {
            "rawSql": "SELECT toStartOfHour(Timestamp) as time, avg(toFloat64OrNull(SpanAttributes['cars.new_count'])) as new_cars_per_hour, avg(toFloat64OrNull(SpanAttributes['cars.after_count'])) as avg_tracked FROM otel_traces WHERE SpanName = 'car_tracking' AND SpanAttributes['cars.new_count'] != '' AND Timestamp >= now() - INTERVAL 24 HOUR GROUP BY time ORDER BY time",
            "refId": "A"
          }
        ],
        "fieldConfig": {
          "defaults": {
            "unit": "short",
            "color": {
              "mode": "palette-classic"
            }
          }
        },
        "gridPos": { "h": 8, "w": 8, "x": 8, "y": 16 }
      },
      {
        "id": 11,
        "title": "ðŸ“ˆ Business KPIs Summary",
        "type": "table",
        "targets": [
          {
            "rawSql": "SELECT 'Today' as Period, count(DISTINCT toDate(Timestamp)) as Days, sum(toFloat64OrNull(SpanAttributes['objects.detected_count'])) as Total_Vehicles, sum(toFloat64OrNull(SpanAttributes['violations.detected_count'])) as Total_Violations, round((sum(toFloat64OrNull(SpanAttributes['violations.detected_count'])) * 100.0 / sum(toFloat64OrNull(SpanAttributes['objects.detected_count']))), 2) as Violation_Rate_Percent FROM otel_traces WHERE (SpanName = 'yolo_inference' OR SpanName = 'stop_detection') AND Timestamp >= today() UNION ALL SELECT 'Last 7 Days' as Period, count(DISTINCT toDate(Timestamp)) as Days, sum(toFloat64OrNull(SpanAttributes['objects.detected_count'])) as Total_Vehicles, sum(toFloat64OrNull(SpanAttributes['violations.detected_count'])) as Total_Violations, round((sum(toFloat64OrNull(SpanAttributes['violations.detected_count'])) * 100.0 / sum(toFloat64OrNull(SpanAttributes['objects.detected_count']))), 2) as Violation_Rate_Percent FROM otel_traces WHERE (SpanName = 'yolo_inference' OR SpanName = 'stop_detection') AND Timestamp >= now() - INTERVAL 7 DAY",
            "refId": "A"
          }
        ],
        "fieldConfig": {
          "defaults": {
            "color": {
              "mode": "palette-classic"
            }
          }
        },
        "gridPos": { "h": 8, "w": 8, "x": 16, "y": 16 }
      },
      {
        "id": 12,
        "title": "ðŸ• Peak Traffic Hours Analysis",
        "type": "heatmap",
        "targets": [
          {
            "rawSql": "SELECT toHour(Timestamp) as hour, toDayOfWeek(Timestamp) as day_of_week, sum(toFloat64OrNull(SpanAttributes['objects.detected_count'])) as vehicle_count FROM otel_traces WHERE SpanName = 'yolo_inference' AND SpanAttributes['objects.detected_count'] != '' AND Timestamp >= now() - INTERVAL 7 DAY GROUP BY hour, day_of_week ORDER BY day_of_week, hour",
            "refId": "A"
          }
        ],
        "gridPos": { "h": 8, "w": 24, "x": 0, "y": 24 }
      }
    ]
  },
  "folderId": 0,
  "overwrite": true
}